vernac/compile.py
vernac/openai.py
vernac/pipeline.py
vernac/util.py
vernac/stages/__init__.py
vernac/stages/all.py
vernac/stages/check_help.py
vernac/stages/check_tests.py
vernac/stages/document_module.py
vernac/stages/generate_code.py
vernac/stages/guess_dependencies.py
vernac/stages/interface.py
vernac/stages/map_modules.py
vernac/stages/package.py
vernac/stages/read_source.py
vernac/stages/run_pipelines.py
vernac/test/__init__.py
vernac/test/test_util.py
vernac-0.0.6.dist-info/LICENSE
vernac-0.0.6.dist-info/METADATA
vernac-0.0.6.dist-info/WHEEL
vernac-0.0.6.dist-info/entry_points.txt
vernac-0.0.6.dist-info/top_level.txt
vernac-0.0.6.dist-info/RECORD
