Metadata-Version: 2.1
Name: vernac
Version: 0.0.6
Summary: Write programs in English
Project-URL: Homepage, https://github.com/bsilverthorn/vernac
Project-URL: Repository, https://github.com/bsilverthorn/vernac
Requires-Python: >=3.10
License-File: LICENSE
Requires-Dist: requests
Requires-Dist: openai
Requires-Dist: shiv
Requires-Dist: tomli-w
Requires-Dist: rich
Requires-Dist: pytest
Requires-Dist: pytest-asyncio
Provides-Extra: dev
Requires-Dist: ipython ; extra == 'dev'
Requires-Dist: pip-tools ; extra == 'dev'
